quick_tts/__init__.py
quick_tts/cli.py
quick_tts/core.py
quick_tts-0.1.2.dist-info/METADATA
quick_tts-0.1.2.dist-info/WHEEL
quick_tts-0.1.2.dist-info/entry_points.txt
quick_tts-0.1.2.dist-info/licenses/LICENSE
quick_tts-0.1.2.dist-info/RECORD
