Metadata-Version: 2.4
Name: quick-tts
Version: 0.1.2
Summary: Convert text to speech using OpenAI's Text-to-Speech API
Project-URL: Homepage, https://github.com/diogoseca/quick-tts
Project-URL: Repository, https://github.com/diogoseca/quick-tts
Project-URL: Issues, https://github.com/diogoseca/quick-tts/issues
Author-email: Diogo Seca <diogoseca@users.noreply.github.com>
License: MIT License
License-File: LICENSE
Keywords: audio,openai,speech,text-to-speech,tts
Classifier: Development Status :: 4 - Beta
Classifier: Intended Audience :: Developers
Classifier: License :: OSI Approved :: MIT License
Classifier: Programming Language :: Python :: 3
Classifier: Programming Language :: Python :: 3.8
Classifier: Programming Language :: Python :: 3.9
Classifier: Programming Language :: Python :: 3.10
Classifier: Programming Language :: Python :: 3.11
Classifier: Programming Language :: Python :: 3.12
Classifier: Topic :: Multimedia :: Sound/Audio :: Speech
Classifier: Topic :: Software Development :: Libraries :: Python Modules
Requires-Python: >=3.8
Requires-Dist: openai>=1.86.0
Requires-Dist: python-dotenv>=1.1.0
